{
  "afghanistan": {
    "title": "Афганистан",
    "images": [
      {
        "filename": "afghanistan_84_anniversaire_de_laviation",
        "alt": "POSTES AFGHANES 40-e ANNIVERSAIRE DE L'AVIATION",
        "category": [
          "Транспорт"
        ],
        "year": 1984
      }
    ]
  },
  "armenia": {
    "title": "Армения",
    "images": [
      {
        "filename": "armenia_vazgen_1",
        "alt": "His Holines Vazgen I",
        "category": [
          "Персонажи"
        ]
      }
    ]
  },
  "belgue": {
    "title": "Бельгия",
    "images": [
      {
        "filename": "belgue_sabena",
        "alt": "BELGIQUE-BELGIE",
        "category": [
          "Транспорт"
        ]
      }
    ]
  },
  "bulgaria": {
    "title": "Болгария",
    "images": [
      {
        "filename": "bulgaria_63_luna_4_2",
        "alt": "ЛУНА-4 N R BULGARIA",
        "category": [
          "Космос"
        ]
      },
      {
        "filename": "bulgaria_63_luna_4",
        "alt": "ЛУНА-4 N R BULGARIA",
        "category": [
          "Космос"
        ]
      }
    ]
  },
  "burundi": {
    "title": "Бурунди",
    "images": [
      {
        "filename": "burundi_nicolas_copernic",
        "alt": "Republique Du Burundi Nicolas Copernic",
        "category": [
          "Персонажи"
        ]
      },
      {
        "filename": "burundi_nicolas_copernic_2",
        "alt": "Republique Du Burundi Nicolas Copernic",
        "category": [
          "Персонажи"
        ]
      }
    ]
  },
  "chile": {
    "title": "Чили",
    "images": [
      {
        "filename": "chile_corero_aereo",
        "alt": "CORREO AEREO-CHILIE",
        "category": [
          "Транспорт"
        ]
      }
    ]
  },
  "cuba": {
    "title": "Куба",
    "images": [
      {
        "filename": "cuba_65_centenario_union_internacional",
        "alt": "1865-1965 CENTENARIO UNION INTERNACIONAL DE TELECOMUNICACIONES CUBA CORREOS",
        "category": [
          "Организации"
        ],
        "year": 1965
      },
      {
        "filename": "cuba_72_munich_olympics",
        "alt": "Boxeo +81 kg. Olympiade #Mönchen",
        "category": [
          "Спорт"
        ],
        "year": 1972
      },
      {
        "filename": "cuba_72_munich_olympics_2",
        "alt": "Boxeo +81 kg. Olympiade #Mönchen",
        "category": [
          "Спорт"
        ],
        "year": 1972
      },
      {
        "filename": "cuba_72_munich_olympics_3",
        "alt": "100 mt. planos F. Olympiade #Mönchen",
        "category": [
          "Спорт"
        ],
        "year": 1972
      },
      {
        "filename": "cuba_72_munich_olympics_4",
        "alt": "Boxeo 54 kg. Olympiade #Mönchen",
        "category": [
          "Спорт"
        ],
        "year": 1972
      },
      {
        "filename": "cuba_72_munich_olympics_5",
        "alt": "Boxeo 67 kg. Olympiade #Mönchen",
        "category": [
          "Спорт"
        ],
        "year": 1972
      },
      {
        "filename": "cuba_72_munich_olympics_6",
        "alt": "Relevo 4x 100 F Olympiade #Mönchen",
        "category": [
          "Спорт"
        ],
        "year": 1972
      },
      {
        "filename": "cuba_75_evolucion_del_ferrocarril_2",
        "alt": "EVOLUCION DELFERROCARRIL",
        "category": [
          "Транспорт"
        ],
        "year": 1975
      },
      {
        "filename": "cuba_75_evolucion_del_ferrocarril_3",
        "alt": "EVOLUCION DELFERROCARRIL",
        "category": [
          "Транспорт"
        ],
        "year": 1975
      },
      {
        "filename": "cuba_75_evolucion_del_ferrocarril",
        "alt": "EVOLUCION DELFERROCARRIL",
        "category": [
          "Транспорт"
        ],
        "year": 1975
      },
      {
        "filename": "cuba_80_olympics_2",
        "alt": "XXII JUEGOS OLIMPICOS MOSCU 80",
        "category": [
          "Спорт"
        ],
        "year": 1980
      },
      {
        "filename": "cuba_80_olympics_3",
        "alt": "XXII JUEGOS OLIMPICOS MOSCU 81",
        "category": [
          "Спорт"
        ],
        "year": 1980
      },
      {
        "filename": "cuba_80_olympics_4",
        "alt": "XXII JUEGOS OLIMPICOS MOSCU 82",
        "category": [
          "Спорт"
        ],
        "year": 1980
      },
      {
        "filename": "cuba_80_olympics_5",
        "alt": "XXII JUEGOS OLIMPICOS MOSCU 83",
        "category": [
          "Спорт"
        ],
        "year": 1980
      },
      {
        "filename": "cuba_80_olympics_6",
        "alt": "XXII JUEGOS OLIMPICOS MOSCU 84",
        "category": [
          "Спорт"
        ],
        "year": 1980
      },
      {
        "filename": "cuba_80_olympics_7",
        "alt": "XXII JUEGOS OLIMPICOS MOSCU 85",
        "category": [
          "Спорт"
        ],
        "year": 1980
      },
      {
        "filename": "cuba_80_olympics_8",
        "alt": "XXII JUEGOS OLIMPICOS MOSCU 86",
        "category": [
          "Спорт"
        ],
        "year": 1980
      },
      {
        "filename": "cuba_80_olympics",
        "alt": "XXII JUEGOS OLIMPICOS MOSCU 87",
        "category": [
          "Спорт"
        ],
        "year": 1980
      }
    ]
  },
  "czech": {
    "title": "Чехия",
    "images": [
      {
        "filename": "czech_57_paris",
        "alt": "Czech 1957 Paris",
        "category": [
          "Транспорт"
        ],
        "year": 1957
      },
      {
        "filename": "czech_57_praha",
        "alt": "Czech 1957 Praha",
        "category": [
          "Транспорт"
        ],
        "year": 1957
      },
      {
        "filename": "czech_60_majstrovstvo_sveta",
        "alt": "Czech 1960 Majstrovstvo Sveta",
        "category": [
          "Транспорт"
        ],
        "year": 1960
      }
    ]
  },
  "france": {
    "title": "Франция",
    "images": [
      {
        "filename": "france_post_aerienne",
        "alt": "REPUBLIQUE FRANCAISE ANOINE DE SAINT-EXUPERY",
        "category": [
          "Транспорт"
        ]
      }
    ]
  },
  "germany": {
    "title": "Германия",
    "images": [
      {
        "filename": "germany_adonis_veri_alis",
        "alt": "Geschützie Prianzen DDR ADONIS VERIALIS / ADON ROSCHEN",
        "category": [
          "Природа"
        ]
      }
    ]
  },
  "hungary": {
    "title": "Венгрия",
    "images": [
      {
        "filename": "hungary_77_boeing_747",
        "alt": "BOEING-747 VERTEL JÓZSEF",
        "category": [
          "Транспорт"
        ],
        "year": 1977
      },
      {
        "filename": "hungary_77_il_62",
        "alt": "IL-62 VERTEL JÓZSEF",
        "category": [
          "Транспорт"
        ],
        "year": 1977
      }
    ]
  },
  "indonesia": {
    "title": "Индонезия",
    "images": [
      {
        "filename": "indonesia_republic",
        "alt": "REPUBLIK INDONESIA",
        "category": [
          "Транспорт"
        ]
      },
      {
        "filename": "indonesia_republic_2",
        "alt": "REPUBLIK INDONESIA",
        "category": [
          "Транспорт"
        ]
      },
      {
        "filename": "indonesia_republic_3",
        "alt": "REPUBLIK INDONESIA",
        "category": [
          "Транспорт"
        ]
      }
    ]
  },
  "mongolia": {
    "title": "Монголия",
    "images": [
      {
        "filename": "mongolia_71_mongol_showdan_30",
        "alt": "MONGOLIA МОНГОЛ ШУУДАН",
        "category": [
          "Персонажи"
        ],
        "year": 1971
      },
      {
        "filename": "mongolia_61_airmail_2",
        "alt": "MONGOLIA",
        "category": [
          "Персонажи",
          "Животные"
        ],
        "year": 1961
      },
      {
        "filename": "mongolia_61_airmail",
        "alt": "MONGOLIA",
        "category": [
          "Персонажи",
          "Животные"
        ],
        "year": 1961
      },
      {
        "filename": "mongolia_71_mongol_showdan_29",
        "alt": "MONGOLIA МОНГОЛ ШУУДАН",
        "category": [
          "Персонажи"
        ],
        "year": 1971
      },
      {
        "filename": "mongolia_71_mongol_showdan_31",
        "alt": "MONGOLIA МОНГОЛ ШУУДАН",
        "category": [
          "Персонажи"
        ],
        "year": 1971
      },
      {
        "filename": "mongolia_71_mongol_showdan_32",
        "alt": "MONGOLIA МОНГОЛ ШУУДАН",
        "category": [
          "Персонажи"
        ],
        "year": 1971
      },
      {
        "filename": "mongolia_71_mongol_showdan_33",
        "alt": "MONGOLIA МОНГОЛ ШУУДАН",
        "category": [
          "Персонажи"
        ],
        "year": 1971
      },
      {
        "filename": "mongolia_71_mongol_showdan_34",
        "alt": "MONGOLIA МОНГОЛ ШУУДАН",
        "category": [
          "Персонажи"
        ],
        "year": 1971
      },
      {
        "filename": "mongolia_71_mongol_showdan_35",
        "alt": "MONGOLIA МОНГОЛ ШУУДАН",
        "category": [
          "Персонажи"
        ],
        "year": 1971
      },
      {
        "filename": "mongolia_71_mongol_showdan_36",
        "alt": "MONGOLIA МОНГОЛ ШУУДАН",
        "category": [
          "Персонажи"
        ],
        "year": 1971
      },
      {
        "filename": "mongolia_72_mongol_showdan_38",
        "alt": "MONGOLIA МОНГОЛ ШУУДАН",
        "category": [
          "Персонажи",
          "Животные"
        ],
        "year": 1972
      },
      {
        "filename": "mongolia_72_mongol_showdan_40",
        "alt": "MONGOLIA МОНГОЛ ШУУДАН",
        "category": [
          "Персонажи"
        ],
        "year": 1972
      },
      {
        "filename": "mongolia_73_mongol_showdan_37",
        "alt": "MONGOLIA МОНГОЛ ШУУДАН",
        "category": [
          "Персонажи"
        ],
        "year": 1973
      },
      {
        "filename": "mongolia_73_mongol_showdan_41",
        "alt": "MONGOLIA МОНГОЛ ШУУДАН",
        "category": [
          "Персонажи"
        ],
        "year": 1973
      },
      {
        "filename": "mongolia_73_mongol_showdan_43",
        "alt": "MONGOLIA МОНГОЛ ШУУДАН",
        "category": [
          "Персонажи"
        ],
        "year": 1973
      },
      {
        "filename": "mongolia_75_mongol_showdan_42",
        "alt": "MONGOLIA МОНГОЛ ШУУДАН",
        "category": [
          "Персонажи"
        ],
        "year": 1975
      },
      {
        "filename": "mongolia_lunik",
        "alt": "MONGOLIA LUNIK МОНГОЛ ШУУДАН",
        "category": [
          "Космос"
        ]
      },
      {
        "filename": "mongolia_mongol_showdan_2",
        "alt": "MONGOLIA МОНГОЛ ШУУДАН",
        "category": [
          "Персонажи"
        ]
      },
      {
        "filename": "mongolia_mongol_showdan_3",
        "alt": "MONGOLIA МОНГОЛ ШУУДАН",
        "category": [
          "Персонажи"
        ]
      },
      {
        "filename": "mongolia_mongol_showdan_4",
        "alt": "MONGOLIA МОНГОЛ ШУУДАН",
        "category": [
          "Персонажи"
        ]
      },
      {
        "filename": "mongolia_mongol_showdan_5",
        "alt": "MONGOLIA МОНГОЛ ШУУДАН",
        "category": [
          "Персонажи"
        ]
      },
      {
        "filename": "mongolia_mongol_showdan_6",
        "alt": "MONGOLIA МОНГОЛ ШУУДАН",
        "category": [
          "Персонажи"
        ]
      },
      {
        "filename": "mongolia_mongol_showdan_7",
        "alt": "MONGOLIA МОНГОЛ ШУУДАН",
        "category": [
          "Персонажи"
        ]
      },
      {
        "filename": "mongolia_mongol_showdan_8",
        "alt": "MONGOLIA МОНГОЛ ШУУДАН",
        "category": [
          "Персонажи",
          "Животные"
        ]
      },
      {
        "filename": "mongolia_mongol_showdan_9",
        "alt": "MONGOLIA МОНГОЛ ШУУДАН",
        "category": [
          "Персонажи",
          "Животные"
        ]
      },
      {
        "filename": "mongolia_mongol_showdan_10",
        "alt": "MONGOLIA МОНГОЛ ШУУДАН",
        "category": [
          "Животные"
        ]
      },
      {
        "filename": "mongolia_mongol_showdan_11",
        "alt": "MONGOLIA МОНГОЛ ШУУДАН",
        "category": [
          "Персонажи"
        ]
      },
      {
        "filename": "mongolia_mongol_showdan_12",
        "alt": "MONGOLIA МОНГОЛ ШУУДАН",
        "category": [
          "Персонажи"
        ]
      },
      {
        "filename": "mongolia_mongol_showdan_13",
        "alt": "MONGOLIA МОНГОЛ ШУУДАН",
        "category": [
          "Персонажи"
        ]
      },
      {
        "filename": "mongolia_mongol_showdan_14",
        "alt": "MONGOLIA МОНГОЛ ШУУДАН",
        "category": [
          "Предметы"
        ]
      },
      {
        "filename": "mongolia_mongol_showdan_15",
        "alt": "MONGOLIA МОНГОЛ ШУУДАН",
        "category": [
          "Предметы"
        ]
      },
      {
        "filename": "mongolia_mongol_showdan_16",
        "alt": "MONGOLIA МОНГОЛ ШУУДАН",
        "category": [
          "Предметы"
        ]
      },
      {
        "filename": "mongolia_mongol_showdan_17",
        "alt": "MONGOLIA МОНГОЛ ШУУДАН",
        "category": [
          "Предметы"
        ]
      },
      {
        "filename": "mongolia_mongol_showdan_18",
        "alt": "MONGOLIA МОНГОЛ ШУУДАН",
        "category": [
          "Предметы"
        ]
      },
      {
        "filename": "mongolia_mongol_showdan_19",
        "alt": "MONGOLIA МОНГОЛ ШУУДАН",
        "category": [
          "Предметы"
        ]
      },
      {
        "filename": "mongolia_mongol_showdan_20",
        "alt": "MONGOLIA МОНГОЛ ШУУДАН",
        "category": [
          "Предметы"
        ]
      },
      {
        "filename": "mongolia_mongol_showdan_21",
        "alt": "MONGOLIA МОНГОЛ ШУУДАН",
        "category": [
          "Персонажи",
          "Животные"
        ]
      },
      {
        "filename": "mongolia_mongol_showdan_22",
        "alt": "MONGOLIA МОНГОЛ ШУУДАН",
        "category": [
          "Животные",
          "Природа"
        ]
      },
      {
        "filename": "mongolia_mongol_showdan_23",
        "alt": "MONGOLIA МОНГОЛ ШУУДАН",
        "category": [
          "Персонажи"
        ]
      },
      {
        "filename": "mongolia_mongol_showdan_24",
        "alt": "MONGOLIA МОНГОЛ ШУУДАН",
        "category": [
          "Персонажи",
          "Животные"
        ]
      },
      {
        "filename": "mongolia_mongol_showdan_25",
        "alt": "MONGOLIA МОНГОЛ ШУУДАН",
        "category": [
          "Персонажи",
          "Животные",
          "Природа"
        ]
      },
      {
        "filename": "mongolia_mongol_showdan_26",
        "alt": "MONGOLIA МОНГОЛ ШУУДАН",
        "category": [
          "Персонажи"
        ]
      },
      {
        "filename": "mongolia_mongol_showdan_27",
        "alt": "MONGOLIA МОНГОЛ ШУУДАН",
        "category": [
          "Природа",
          "Животные"
        ]
      },
      {
        "filename": "mongolia_mongol_showdan_28",
        "alt": "MONGOLIA МОНГОЛ ШУУДАН",
        "category": [
          "Персонажи"
        ]
      },
      {
        "filename": "mongolia_mongol_showdan_39",
        "alt": "MONGOLIA МОНГОЛ ШУУДАН",
        "category": [
          "Персонажи",
          "Природа",
          "Животные"
        ]
      },
      {
        "filename": "mongolia_mongol_showdan",
        "alt": "MONGOLIA МОНГОЛ ШУУДАН",
        "category": [
          "Персонажи"
        ]
      },
      {
        "filename": "mongolia_tiros",
        "alt": "MONGOLIA TIROS",
        "category": [
          "Космос"
        ]
      }
    ]
  },
  "oman": {
    "title": "Оман",
    "images": [
      {
        "filename": "oman_5",
        "alt": "POSTAGE STATE OF OMAN",
        "category": [
          "Животные"
        ]
      },
      {
        "filename": "oman_1",
        "alt": "POSTAGE STATE OF OMAN",
        "category": [
          "Животные"
        ]
      },
      {
        "filename": "oman_2",
        "alt": "POSTAGE STATE OF OMAN",
        "category": [
          "Животные"
        ]
      },
      {
        "filename": "oman_3",
        "alt": "POSTAGE STATE OF OMAN",
        "category": [
          "Животные"
        ]
      },
      {
        "filename": "oman_4",
        "alt": "POSTAGE STATE OF OMAN",
        "category": [
          "Животные"
        ]
      }
    ]
  },
  "poland": {
    "title": "Польша",
    "images": [
      {
        "filename": "poland_07_1",
        "alt": "Polska MARECKA KOLEJ DOJAZDOWA ",
        "category": [
          "Транспорт"
        ],
        "year": 1907
      },
      {
        "filename": "poland_1",
        "alt": "Polska",
        "category": [
          "Животные"
        ]
      },
      {
        "filename": "poland_2",
        "alt": "Polska",
        "category": [
          "Животные"
        ]
      },
      {
        "filename": "poland_3",
        "alt": "Polska",
        "category": [
          "Животные"
        ]
      },
      {
        "filename": "poland_07_2",
        "alt": "Polska MARECKA KOLEJ DOJAZDOWA ",
        "category": [
          "Транспорт"
        ],
        "year": 1907
      },
      {
        "filename": "poland_32_rwd_6_zwirko",
        "alt": "POLSKA CHALLENGE RWD-6 F. ZWIRKO. S. WIGURA",
        "category": [
          "Транспорт"
        ],
        "year": 1932
      },
      {
        "filename": "poland_34_rwd_9_bajan",
        "alt": "POLSKA CHALLENGE RWD-9 J. BAJAN, G POKRZYWKA",
        "category": [
          "Транспорт"
        ],
        "year": 1934
      },
      {
        "filename": "poland_57_eletryfikacja_linii",
        "alt": "Polska ELEKTRYFIKACJA LINII WARSZAWA SLASK",
        "category": [
          "Транспорт"
        ],
        "year": 1957
      },
      {
        "filename": "poland_69_et_22",
        "alt": "Polska Uniwersalna lokomotywa elektryczn BT-22",
        "category": [
          "Транспорт"
        ],
        "year": 1969
      },
      {
        "filename": "poland_76_aleksander_czekanowski",
        "alt": "Aleksander Czekanowski",
        "category": [
          "Персонажи"
        ],
        "year": 1976
      },
      {
        "filename": "poland_76_stephenson",
        "alt": "POLSKA G. Stephenson S. MALECKI PWPW 76.",
        "category": [
          "Транспорт"
        ],
        "year": 1976
      },
      {
        "filename": "poland_79_platichthys_flesus",
        "alt": "ATICHTHYS FLESUS L. Fladra",
        "category": [
          "Животные"
        ],
        "year": 1979
      },
      {
        "filename": "poland_79_salmo_truttaf",
        "alt": "SALMO TRUTTA F. FARIO L. Pstrag",
        "category": [
          "Животные"
        ],
        "year": 1979
      },
      {
        "filename": "poland_klon",
        "alt": "Klon zwyczajny Acer platanoides",
        "category": [
          "Природа"
        ]
      },
      {
        "filename": "poland_polonez_fso",
        "alt": "Polonez FSO",
        "category": [
          "Транспорт"
        ]
      },
      {
        "filename": "poland_topola",
        "alt": "Topola biata Populus alba",
        "category": [
          "Природа"
        ]
      },
      {
        "filename": "poland_warszawa_m_20",
        "alt": "WARSZAWA M20",
        "category": [
          "Транспорт"
        ]
      }
    ]
  },
  "russia": {
    "title": "Россия",
    "images": [
      {
        "filename": "russia_2000_ganover",
        "alt": "ЭКСПО Ганновер ROSSIJA-2000",
        "category": [
          "Места"
        ],
        "year": 2000
      }
    ]
  },
  "spain": {
    "title": "Испания",
    "images": [
      {
        "filename": "espana_correro_aereo",
        "alt": "ESPANA CORREO AEREO",
        "category": [
          "Транспорт"
        ]
      },
      {
        "filename": "espana_correro_aereo_2",
        "alt": "ESPANA CORREO AEREO",
        "category": [
          "Транспорт"
        ]
      },
      {
        "filename": "espana_correro_aereo_3",
        "alt": "ESPANA CORREO AEREO",
        "category": [
          "Транспорт"
        ]
      },
      {
        "filename": "espana_correro_aereo_4",
        "alt": "ESPANA CORREO AEREO",
        "category": [
          "Транспорт"
        ]
      },
      {
        "filename": "espana_correro_aereo_5",
        "alt": "ESPANA CORREO AEREO",
        "category": [
          "Транспорт"
        ]
      }
    ]
  },
  "suriname": {
    "title": "Суринам",
    "images": [
      {
        "filename": "suriname_stichting_lucht_en_2",
        "alt": "STICHTING LUCHT- EN US AIR FORCE RUIMTEVAART SURINAME",
        "category": [
          "Транспорт"
        ]
      },
      {
        "filename": "suriname_stichting_lucht_en_3",
        "alt": "STICHTING LUCHT- EN US AIR FORCE RUIMTEVAART SURINAME",
        "category": [
          "Космос"
        ]
      },
      {
        "filename": "suriname_stichting_lucht_en_4",
        "alt": "STICHTING LUCHT- EN US AIR FORCE RUIMTEVAART SURINAME",
        "category": [
          "Транспорт"
        ]
      },
      {
        "filename": "suriname_stichting_lucht_en_5",
        "alt": "STICHTING LUCHT- EN US AIR FORCE RUIMTEVAART SURINAME",
        "category": [
          "Космос"
        ]
      },
      {
        "filename": "suriname_stichting_lucht_en",
        "alt": "STICHTING LUCHT- EN US AIR FORCE RUIMTEVAART SURINAME",
        "category": [
          "Космос"
        ]
      }
    ]
  },
  "swiss": {
    "title": "Швейцария",
    "images": [
      {
        "filename": "swiss_53_swissair",
        "alt": "SWISS AIR HELVETIA PIERRE GAUCHAT COURVOISIER S",
        "category": [
          "Транспорт"
        ],
        "year": 1953
      }
    ]
  },
  "turkey": {
    "title": "Турция",
    "images": [
      {
        "filename": "turkey_67_cumhuriyeti_2",
        "alt": "ATLAR MATBAASI - ISTANBUL",
        "category": [
          "Транспорт"
        ],
        "year": 1967
      },
      {
        "filename": "turkey_67_cumhuriyeti",
        "alt": "ATLAR MATBAASI - ISTANBUL",
        "category": [
          "Транспорт"
        ],
        "year": 1967
      }
    ]
  },
  "uruguay": {
    "title": "Уругвай",
    "images": [
      {
        "filename": "uruguay_correro_aereo",
        "alt": "Correro Aereo Republica O.del Uruguay IMP.NACIONAL",
        "category": [
          "Транспорт"
        ]
      },
      {
        "filename": "uruguay_correro_aereo_2",
        "alt": "Correro Aereo Republica O.del Uruguay IMP.NACIONAL",
        "category": [
          "Транспорт"
        ]
      },
      {
        "filename": "uruguay_correro_aereo_3",
        "alt": "Correro Aereo Republica O.del Uruguay IMP.NACIONAL",
        "category": [
          "Транспорт"
        ]
      },
      {
        "filename": "uruguay_correro_aereo_4",
        "alt": "Correro Aereo Republica O.del Uruguay IMP.NACIONAL",
        "category": [
          "Транспорт"
        ]
      }
    ]
  },
  "ussr": {
    "title": "СССР",
    "images": [
      {
        "filename": "ussr_61_40_let_sovetskoy_pochtovoy_marke",
        "alt": "40 ЛЕТ СОВЕТСКОЙ ПОЧТОВОЙ МАРКЕ ЛЕНИН",
        "category": [
          "Организации"
        ],
        "year": 1961
      },
      {
        "filename": "ussr_62_flamingo",
        "alt": "ФЛАМИНГО",
        "category": [
          "Животные"
        ],
        "year": 1962
      },
      {
        "filename": "ussr_62_krasnozobaya_kazarka",
        "alt": "КРАСНОЗОБАЯ КАЗАРКА",
        "category": [
          "Животные"
        ],
        "year": 1962
      },
      {
        "filename": "ussr_66_itkol",
        "alt": "ТУРИСТСКИЙ КОМПЛЕКО «ИТКОЛ»",
        "category": [
          "Места"
        ],
        "year": 1966
      },
      {
        "filename": "ussr_70_chuvashskoi_assr",
        "alt": "50 ЛЕТ ЧУВАШСКОЙ АССР",
        "category": [
          "Места"
        ],
        "year": 1970
      },
      {
        "filename": "ussr_70_kalmytskaya_assr",
        "alt": "50 ЛЕТ КАЛМЫТСКОЙ АССР",
        "category": [
          "Места"
        ],
        "year": 1970
      },
      {
        "filename": "ussr_70_karelskaya_assr",
        "alt": "50 ЛЕТ КАРЕЛЬСКОЙ АССР",
        "category": [
          "Места"
        ],
        "year": 1970
      },
      {
        "filename": "ussr_70_mandarinka",
        "alt": "Мандаринка СИХОТЭ АЛИНСКИЙ ЗАПОВЕДНИК",
        "category": [
          "Животные"
        ],
        "year": 1970
      },
      {
        "filename": "ussr_70_mariyskaya_assr",
        "alt": "50 ЛЕТ МАРИЙСКОЙ АССР",
        "category": [
          "Места"
        ],
        "year": 1970
      },
      {
        "filename": "ussr_70_tatarskaya_assr",
        "alt": "50 ЛЕТ ТАТАРСКОЙ АССР",
        "category": [
          "Места"
        ],
        "year": 1970
      },
      {
        "filename": "ussr_70_udmurtskaya_assr",
        "alt": "50 ЛЕТ УДМУРТСКОЙ АССР",
        "category": [
          "Места"
        ],
        "year": 1970
      },
      {
        "filename": "ussr_71_adzharskaya_assr",
        "alt": "50 ЛЕТ АДЖАРСКОЙ АССР",
        "category": [
          "Места"
        ],
        "year": 1971
      },
      {
        "filename": "ussr_71_almazniy_fond",
        "alt": "БУКЕТ НАРЦИСОВ АЛМАЗНЫЙ ФОНД ССР",
        "category": [
          "Предметы"
        ],
        "year": 1971
      },
      {
        "filename": "ussr_71_dagestanskaya_assr",
        "alt": "50 ЛЕТ ДАГЕСТАНСКОЙ АССР",
        "category": [
          "Места"
        ],
        "year": 1971
      },
      {
        "filename": "ussr_71_federatsiya_bortsov_soprotivleniya",
        "alt": "XXЛЕТ МЕЖДУНАРОДНОЙ ФЕДЕРАЦИИ БОРЦОВ СОПРОТИВЛЕНИЯ",
        "category": [
          "Организации"
        ],
        "year": 1971
      },
      {
        "filename": "ussr_71_kabardino_balkarskaya_assr",
        "alt": "50 ЛЕТ КАБАРДИНО-БАЛКАРСКОЙ АССР",
        "category": [
          "Места"
        ],
        "year": 1971
      },
      {
        "filename": "ussr_72_checheno_ingushkaya_assr",
        "alt": "50 ЛЕТ ЧЕЧЕНО-ИНГУШСКОЙ АССР",
        "category": [
          "Места"
        ],
        "year": 1971
      },
      {
        "filename": "ussr_72_chernogolovaya_chaika",
        "alt": "ЧЕРНОГОЛОВАЯ ЧАЙКА",
        "category": [
          "Животные"
        ],
        "year": 1971
      },
      {
        "filename": "ussr_72_rozovaya_chayka",
        "alt": "РОЗОВАЯ ЧАЙКА",
        "category": [
          "Животные"
        ],
        "year": 1971
      },
      {
        "filename": "ussr_73_buryatskaya_assr",
        "alt": "50 ЛЕТ БУРЯТСКОЙ АССР",
        "category": [
          "Места"
        ],
        "year": 1971
      },
      {
        "filename": "ussr_73_gaz_a_1932",
        "alt": "ГАЗ-А 1932",
        "category": [
          "Транспорт"
        ],
        "year": 1971
      },
      {
        "filename": "ussr_73_kongress_mirolubivyh_sil",
        "alt": "ВСЕМИРНЫЙ КОНГРЕСС МИРОЛЮБИВЫХ СИЛ",
        "category": [
          "Организации"
        ],
        "year": 1971
      },
      {
        "filename": "ussr_73_olen",
        "alt": "ОЛЕНЬ ВОРОНЕЖСКИЙ ЗАПОВЕДНИК",
        "category": [
          "Животные"
        ],
        "year": 1971
      },
      {
        "filename": "ussr_73_tur",
        "alt": "ТУР КАВКАЗСКИЙ ЗАПОВЕДНИК",
        "category": [
          "Животные"
        ],
        "year": 1971
      },
      {
        "filename": "ussr_73_ular",
        "alt": "УЛАР КАВКАЗСКИЙ ЗАПОВЕДНИК",
        "category": [
          "Животные"
        ],
        "year": 1971
      },
      {
        "filename": "ussr_73_university_moscow",
        "alt": "УНИВЕРСИАДА МОСКВА",
        "category": [
          "Спорт"
        ],
        "year": 1971
      },
      {
        "filename": "ussr_73_ya_6_1929",
        "alt": "Я-6 1929 ",
        "category": [
          "Транспорт"
        ],
        "year": 1971
      },
      {
        "filename": "ussr_74_800_let_poltave",
        "alt": "800 лет городу Полтаве",
        "category": [
          "Места"
        ],
        "year": 1974
      },
      {
        "filename": "ussr_74_expo",
        "alt": "ЭКСПО'74 ВСЕ ДЛЯ ЧЕЛОВЕКА, РАДИ ЕГО БУДУЩЕГО",
        "category": [
          "Животные"
        ],
        "year": 1974
      },
      {
        "filename": "ussr_74_gaz_03_30_1933",
        "alt": "ГАЗ-03-30 1933",
        "category": [
          "Транспорт"
        ],
        "year": 1974
      },
      {
        "filename": "ussr_74_grenlandskiy_kit",
        "alt": "ITC ПЕРВЫЙ МЕЖДУНАРОДНЫЙ ТЕХНОЛОГИЧЕСКИЙ КОНГРЕСС Грендланский кит",
        "category": [
          "Животные"
        ],
        "year": 1974
      },
      {
        "filename": "ussr_74_kulan",
        "alt": "ITC ПЕРВЫЙ МЕЖДУНАРОДНЫЙ ТЕХНОЛОГИЧЕСКИЙ КОНГРЕСС Кулан",
        "category": [
          "Животные"
        ],
        "year": 1974
      },
      {
        "filename": "ussr_74_morskoy_kotik",
        "alt": "ITC ПЕРВЫЙ МЕЖДУНАРОДНЫЙ ТЕХНОЛОГИЧЕСКИЙ КОНГРЕСС Морской котик",
        "category": [
          "Животные"
        ],
        "year": 1974
      },
      {
        "filename": "ussr_74_nahichivanskaya_assr",
        "alt": "50 ЛЕТ НАХИЧЕВАНСКОЙ АССР",
        "category": [
          "Места"
        ],
        "year": 1974
      },
      {
        "filename": "ussr_74_saygak",
        "alt": "ITC ПЕРВЫЙ МЕЖДУНАРОДНЫЙ ТЕХНОЛОГИЧЕСКИЙ КОНГРЕСС Сайгак",
        "category": [
          "Животные"
        ],
        "year": 1974
      },
      {
        "filename": "ussr_74_severnaya_osetia_assr",
        "alt": "200 - ЛЕТИЕ ДОБРОВОЛЬНОГО ПРИСОЕДИНЕНИЯ ОСЕТИИ К РОССИИ 50 ЛET АВТОНОМИИ СЕВЕРО-ОСЕТИНСКОЙ ACCP",
        "category": [
          "Места"
        ],
        "year": 1974
      },
      {
        "filename": "ussr_74_turkmenskaya_ssr",
        "alt": "ТУРКМЕНСКАЯ ССР",
        "category": [
          "Места"
        ],
        "year": 1974
      },
      {
        "filename": "ussr_74_uzbekskaya_ssr",
        "alt": "УЗБЕКСКАЯ ССР",
        "category": [
          "Места"
        ],
        "year": 1974
      },
      {
        "filename": "ussr_74_vihuhol",
        "alt": "ITC ПЕРВЫЙ МЕЖДУНАРОДНЫЙ ТЕХНОЛОГИЧЕСКИЙ КОНГРЕСС Выхухоль",
        "category": [
          "Животные"
        ],
        "year": 1974
      },
      {
        "filename": "ussr_74_zis_5_1993",
        "alt": "ЗИС-5 1993",
        "category": [
          "Транспорт"
        ],
        "year": 1974
      },
      {
        "filename": "ussr_74_zis_8_1934",
        "alt": "ЗИС-8 1934",
        "category": [
          "Транспорт"
        ],
        "year": 1974
      },
      {
        "filename": "ussr_74_zis_101_1936",
        "alt": "ЗИС-101 1936",
        "category": [
          "Транспорт"
        ],
        "year": 1974
      },
      {
        "filename": "ussr_75_expo_2",
        "alt": "Моря Дальнего Востока Камчатский краб",
        "category": [
          "Животные"
        ],
        "year": 1975
      },
      {
        "filename": "ussr_75_expo_3",
        "alt": "Черное море Рапана",
        "category": [
          "Животные"
        ],
        "year": 1975
      },
      {
        "filename": "ussr_75_expo_4",
        "alt": "Каспийское море Осетр",
        "category": [
          "Животные"
        ],
        "year": 1975
      },
      {
        "filename": "ussr_75_expo_5",
        "alt": "Бассейн Тихого океана Хризиптера Chrysiptera hollisi",
        "category": [
          "Животные"
        ],
        "year": 1975
      },
      {
        "filename": "ussr_75_expo",
        "alt": "Балтиское Море Угорь",
        "category": [
          "Животные"
        ],
        "year": 1975
      },
      {
        "filename": "ussr_75_gaz_76b_1943",
        "alt": "ГАЗ-76Б 1943",
        "category": [
          "Транспорт"
        ],
        "year": 1975
      },
      {
        "filename": "ussr_75_gaz_m_1_1936",
        "alt": "ГАЗ-М-1 1936",
        "category": [
          "Транспорт"
        ],
        "year": 1975
      },
      {
        "filename": "ussr_75_karakalpaskaya_assr",
        "alt": "50 ЛЕТ КАРАКАЛПАКСКОЙ АССР",
        "category": [
          "Места"
        ],
        "year": 1975
      },
      {
        "filename": "ussr_75_kim_10_1940",
        "alt": "КИМ-10 1940",
        "category": [
          "Транспорт"
        ],
        "year": 1975
      },
      {
        "filename": "ussr_75_yag_3_1936",
        "alt": "ЯГ-3 1936",
        "category": [
          "Транспорт"
        ],
        "year": 1975
      },
      {
        "filename": "ussr_76_gaz_51_1946",
        "alt": "ГАЗ-51 1946",
        "category": [
          "Транспорт"
        ],
        "year": 1976
      },
      {
        "filename": "ussr_76_souz_19_apallon",
        "alt": "СОЮЗ-19 АПОЛЛОН СОТРУДНИЧЕСТВО В КОСМОСЕ СССР и США",
        "category": [
          "Космос"
        ],
        "year": 1976
      },
      {
        "filename": "ussr_76_trenev",
        "alt": "К.А.ТРЕНЕВ СОВЕТСКИЙ ДРАМАТУРГ 1876-1945",
        "category": [
          "Персонажи"
        ],
        "year": 1976
      },
      {
        "filename": "ussr_76_zis_110_1945",
        "alt": "ЗИС-110 1945",
        "category": [
          "Транспорт"
        ],
        "year": 1976
      },
      {
        "filename": "ussr_76_zis_150_1947",
        "alt": "ЗИС-150 1947",
        "category": [
          "Транспорт"
        ],
        "year": 1976
      },
      {
        "filename": "ussr_77_efa",
        "alt": "ЭФА ПЕСЧАНАЯ ЯДОВИТЫЕ ЗМЕИ ПОЛЕЗНЫЕ ПРЕДСТАВИТЕЛИ ФАУНЫ",
        "category": [
          "Животные"
        ],
        "year": 1977
      },
      {
        "filename": "ussr_77_gadyka",
        "alt": "ГАДЮКА ОБЫКНОВЕННАЯ ЯДОВИТЫЕ ЗМЕИ ПОЛЕЗНЫЕ ПРЕДСТАВИТЕЛИ ФАУНЫ",
        "category": [
          "Животные"
        ],
        "year": 1977
      },
      {
        "filename": "ussr_77_gurza",
        "alt": "ГЮРЗА ПОЛЕЗНЫЕ ПРЕДСТАВИТЕЛИ ФАУНЫ",
        "category": [
          "Животные"
        ],
        "year": 1977
      },
      {
        "filename": "ussr_77_kobra",
        "alt": "КОБРА СРЕДНЕАЗИАТСКАЯ ПОЛЕЗНЫЕ ПРЕДСТАВИТЕЛИ ФАУНЫ",
        "category": [
          "Животные"
        ],
        "year": 1977
      },
      {
        "filename": "ussr_77_shitomordnik",
        "alt": "ЩИТОМОРДНИК ОБЫКНОВЕННЫЙ ЯДОВИТЫЕ ЗМЕИ ПОЛЕЗНЫЕ ПРЕДСТАВИТЕЛИ ФАУНЫ",
        "category": [
          "Животные"
        ],
        "year": 1977
      },
      {
        "filename": "ussr_78_imperatorskiy_pingvin",
        "alt": "ИМПЕРАТОРСКИЙ ПИНГВИН",
        "category": [
          "Животные"
        ],
        "year": 1978
      },
      {
        "filename": "ussr_78_morskoi_slon",
        "alt": "МОРСКОЙ СЛОН",
        "category": [
          "Животные"
        ],
        "year": 1978
      },
      {
        "filename": "ussr_78_passazhirskiy_paravoz",
        "alt": "ПЕРВЫЙ ПАССАЖИРСКИЙ ПАРОВОЗ типа 2-2-0 серии В 1845",
        "category": [
          "Транспорт"
        ],
        "year": 1978
      },
      {
        "filename": "ussr_78_shuka",
        "alt": "БЕЛОКРОВНАЯ ЩУКА",
        "category": [
          "Животные"
        ],
        "year": 1978
      },
      {
        "filename": "ussr_78_snezhniy_burevestnik",
        "alt": "СНЕЖНЫЙ БУРЕВЕСТНИК",
        "category": [
          "Животные"
        ],
        "year": 1978
      },
      {
        "filename": "ussr_78_tovarniy_poezd",
        "alt": "ТОВАРНЫЙ ПАРОВОЗ типа 3-0 серии Д 1845",
        "category": [
          "Транспорт"
        ],
        "year": 1978
      },
      {
        "filename": "ussr_78_zhertokryliy_pingvin",
        "alt": "ЖЕЛТОХОХЛЫЙ ПИНГВИН",
        "category": [
          "Животные"
        ],
        "year": 1978
      },
      {
        "filename": "ussr_79_interkosmos_2",
        "alt": "МЕЖДУНАРОДНЫЕ ПОЛЕТЫ В КОСМОС",
        "category": [
          "Космос"
        ],
        "year": 1979
      },
      {
        "filename": "ussr_79_interkosmos",
        "alt": "МЕЖДУНАРОДНЫЕ ПОЛЕТЫ В КОСМОС",
        "category": [
          "Космос"
        ],
        "year": 1979
      },
      {
        "filename": "ussr_80_olympics_2",
        "alt": "XIII ЗИМНИЕ ОЛИМПИЙСКИЕ ИГРЫ ЛЕЙК-ПЛЭСИД",
        "category": [
          "Спорт"
        ],
        "year": 1980
      },
      {
        "filename": "ussr_80_olympics_3",
        "alt": "XIII ЗИМНИЕ ОЛИМПИЙСКИЕ ИГРЫ ЛЕЙК-ПЛЭСИД",
        "category": [
          "Спорт"
        ],
        "year": 1980
      },
      {
        "filename": "ussr_80_olympics_4",
        "alt": "XIII ЗИМНИЕ ОЛИМПИЙСКИЕ ИГРЫ ЛЕЙК-ПЛЭСИД",
        "category": [
          "Спорт"
        ],
        "year": 1980
      },
      {
        "filename": "ussr_80_olympics_5",
        "alt": "XIII ЗИМНИЕ ОЛИМПИЙСКИЕ ИГРЫ ЛЕЙК-ПЛЭСИД",
        "category": [
          "Спорт"
        ],
        "year": 1980
      },
      {
        "filename": "ussr_80_olympics",
        "alt": "XIII ЗИМНИЕ ОЛИМПИЙСКИЕ ИГРЫ ЛЕЙК-ПЛЭСИД",
        "category": [
          "Спорт"
        ],
        "year": 1980
      },
      {
        "filename": "ussr_80_pesets",
        "alt": "Ценные попроды пушных зверей Песец вуалевый",
        "category": [
          "Животные"
        ],
        "year": 1980
      },
      {
        "filename": "ussr_day_of_vvs",
        "alt": "ПЕНЬ ВОЗДУШНОГО ФЛОТА СССР",
        "category": [
          "Транспорт"
        ]
      },
      {
        "filename": "ussr_hockey",
        "alt": "Хоккей",
        "category": [
          "Спорт"
        ]
      },
      {
        "filename": "ussr_il_14",
        "alt": "СМОЛЕТ ИЛ-14",
        "category": [
          "Транспорт"
        ]
      },
      {
        "filename": "ussr_il_18",
        "alt": "ТУРБОВИНТОВОЙ САМОЛЕТ ИЛ-18",
        "category": [
          "Транспорт"
        ]
      },
      {
        "filename": "ussr_tu_104",
        "alt": "ТУРБОРЕАКТИВНЫЙ САМОЛЕТ ТУ-104",
        "category": [
          "Транспорт"
        ]
      },
      {
        "filename": "ussr_tu_110",
        "alt": "ТУРБОРЕАКТИВНЫЙ САМОЛЕТ ТУ-110",
        "category": [
          "Транспорт"
        ]
      },
      {
        "filename": "ussr_tu_114",
        "alt": "ТУРБОВИНТОВОЙ САМОЛЕТ ТУ-114",
        "category": [
          "Транспорт"
        ]
      },
      {
        "filename": "ussr_tu_an_10",
        "alt": "ТУРБОВИНТОВОЙ САМОЛЕТ АН-10",
        "category": [
          "Транспорт"
        ]
      }
    ]
  },
  "vietnam": {
    "title": "Вьетнам",
    "images": [
      {
        "filename": "vietnam_tyrannosaurus",
        "alt": "THÄN LÄN SÄM 20 ",
        "category": [
          "Животные"
        ]
      },
      {
        "filename": "vietnam_brontosaurus",
        "alt": "THÄN LÄN SÄM 12 ",
        "category": [
          "Животные"
        ]
      },
      {
        "filename": "vietnam_iguanodon",
        "alt": "THÄN LÄN AN CO 20",
        "category": [
          "Животные"
        ]
      },
      {
        "filename": "vietnam_mozasaurus",
        "alt": "THÄN LÄN CÁ 50 ",
        "category": [
          "Животные"
        ]
      },
      {
        "filename": "vietnam_plesiosaurus",
        "alt": "THÄN LÄN RUA CORÄN 12 ",
        "category": [
          "Животные"
        ]
      },
      {
        "filename": "vietnam_pteranodon",
        "alt": "THÄN LÄN CO CÁNH 1,00",
        "category": [
          "Животные"
        ]
      },
      {
        "filename": "vietnam_stecosaurus",
        "alt": "THÄN LÄN GAI DUÖI 40",
        "category": [
          "Животные"
        ]
      },
      {
        "filename": "vietnam_triceratop",
        "alt": "THÄN LÄN BA SÜNG 60",
        "category": [
          "Животные"
        ]
      }
    ]
  },
  "yemen": {
    "title": "Йемен",
    "images": [
      {
        "filename": "yemen_honouring_astronauts",
        "alt": "1/2B. AIR MAIL YEMEN ARAB REPUBLIC HONOURING ASTRONAUTS",
        "category": [
          "Космос"
        ]
      },
      {
        "filename": "yemen_honouring_astronauts_2",
        "alt": "1/4B. AIR MAIL YEMEN ARAB REPUBLIC HONOURING ASTRONAUTS",
        "category": [
          "Космос"
        ]
      },
      {
        "filename": "yemen_honouring_astronauts_3",
        "alt": "1/3B. AIR MAIL YEMEN ARAB REPUBLIC HONOURING ASTRONAUTS",
        "category": [
          "Космос"
        ]
      }
    ]
  },
  "yugoslavia": {
    "title": "Югославия",
    "images": [
      {
        "filename": "yugoslavia_fnr",
        "alt": "ФНР Jyгославиja 1 DIN",
        "category": [
          "Транспорт"
        ]
      },
      {
        "filename": "yugoslavia_fnr_2",
        "alt": "ФНР Jyгославиja 2 DIN",
        "category": [
          "Транспорт"
        ]
      }
    ]
  }
}